odoo9_addon_cms_form_example-9.0.1.0.0-py2.7-nspkg.pth
odoo9_addon_cms_form_example-9.0.1.0.0.dist-info/DESCRIPTION.rst
odoo9_addon_cms_form_example-9.0.1.0.0.dist-info/METADATA
odoo9_addon_cms_form_example-9.0.1.0.0.dist-info/RECORD
odoo9_addon_cms_form_example-9.0.1.0.0.dist-info/WHEEL
odoo9_addon_cms_form_example-9.0.1.0.0.dist-info/metadata.json
odoo9_addon_cms_form_example-9.0.1.0.0.dist-info/namespace_packages.txt
odoo9_addon_cms_form_example-9.0.1.0.0.dist-info/top_level.txt
odoo_addons/cms_form_example/README.rst
odoo_addons/cms_form_example/__init__.py
odoo_addons/cms_form_example/__openerp__.py
odoo_addons/cms_form_example/controllers/__init__.py
odoo_addons/cms_form_example/controllers/main.py
odoo_addons/cms_form_example/models/__init__.py
odoo_addons/cms_form_example/models/partner.py
odoo_addons/cms_form_example/static/description/icon.png
odoo_addons/cms_form_example/static/src/js/cms_form_example.tour.js
odoo_addons/cms_form_example/templates/assets.xml
